ask_openai/__.py
ask_openai/__init__.py
ask_openai-0.1.7.dist-info/WHEEL
ask_openai-0.1.7.dist-info/METADATA
ask_openai-0.1.7.dist-info/RECORD
