Metadata-Version: 2.1
Name: ask-openai
Version: 0.1.7
Summary: Explain exceptions using OpenAI / GPT-3
Home-page: https://github.com/numpde/ask_openai
Author: RA
Author-email: numpde@null.net
Requires-Python: >=3.7,<4.0
Classifier: Programming Language :: Python :: 3
Classifier: Programming Language :: Python :: 3.7
Classifier: Programming Language :: Python :: 3.8
Classifier: Programming Language :: Python :: 3.9
Classifier: Programming Language :: Python :: 3.10
Classifier: Programming Language :: Python :: 3.11
Project-URL: Repository, https://github.com/numpde/ask_openai
